{"result":{"2":[],"3":[],"6":[],"13":[],"15":[],"16":[],"17":[],"18":[],"19":[],"22":[],"23":[],"24":[],"25":[],"26":[],"27":[],"28":[],"29":[],"30":[],"31":[],"32":[],"33":[],"34":[],"35":[],"36":[],"37":[],"38":[],"39":[],"40":[],"41":[],"42":[],"43":[],"44":[],"45":[],"46":[],"47":[],"48":[],"49":[],"50":[],"51":[],"52":[],"53":[],"54":[],"55":[],"56":[],"60":[],"61":[],"62":[],"63":[],"64":[],"65":[],"66":[],"67":[],"68":[],"69":[],"70":[],"71":[],"72":[],"73":[],"74":[],"75":[],"76":[],"77":[],"78":[],"79":[],"80":[],"81":[],"82":[],"83":[],"84":[],"85":[],"86":[],"88":[],"89":[],"91":[],"92":[],"93":[],"94":[],"96":[],"97":[],"98":[],"99":[],"100":[],"102":[],"103":[],"104":[],"105":[],"106":[],"107":[],"108":[],"110":[],"112":[],"116":[],"117":[],"120":[],"121":[],"122":[],"123":[],"125":[],"126":[],"127":[],"128":[],"129":[],"130":[],"131":[],"132":[],"133":[],"135":[],"136":[],"137":[],"138":[],"139":[],"141":[],"142":[],"143":[],"144":[],"145":[],"146":[],"147":[],"148":[],"149":[],"150":[],"151":[],"153":[],"154":[],"155":[],"156":[],"157":[],"159":[],"160":[],"161":[],"163":[],"164":[],"165":[],"166":[],"167":[],"169":[],"170":[],"171":[],"173":[],"174":[],"175":[],"176":[],"177":[],"178":[],"179":[],"180":[],"181":[],"182":[],"184":[],"186":[],"187":[],"188":[],"189":[],"190":[],"192":[],"193":[],"194":[],"195":[],"196":[],"197":[],"198":[],"199":[],"200":[],"201":[],"202":[],"203":[],"204":[],"205":[],"206":[],"207":[],"208":[],"209":[],"211":[],"212":[],"213":[],"214":[],"215":[],"217":[],"218":[],"219":[],"221":[],"222":[],"223":[],"224":[],"225":[],"226":[],"227":[],"228":[],"229":[],"230":[],"231":[],"232":[],"233":[],"234":[],"235":[],"236":[],"237":[],"238":[],"239":[],"240":[],"241":[],"242":[],"243":[],"244":[],"245":[],"246":[],"247":[],"248":[],"249":[],"250":[],"251":[],"253":[],"254":[],"255":[],"256":[],"257":[],"258":[],"259":[],"260":[],"261":[],"262":[],"263":[],"264":[],"265":[],"266":[],"267":[],"268":[],"269":[],"270":[],"271":[],"272":[],"273":[],"274":[],"275":[],"276":[],"277":[],"278":[],"279":[],"280":[],"281":[],"282":[],"283":[],"284":[],"285":[],"286":[],"287":[],"288":[],"289":[],"290":[],"292":[],"293":[],"294":[],"295":[],"296":[],"297":[],"298":[],"299":[],"300":[],"301":[],"302":[],"303":[],"304":[],"305":[],"307":[],"308":[],"309":[],"310":[],"311":[],"312":[],"313":[],"314":[],"315":[],"316":[],"317":[],"318":[],"319":[],"320":[],"321":[],"322":[],"323":[],"324":[],"325":[],"326":[],"327":[],"328":[],"329":[],"330":[],"331":[],"332":[],"333":[],"334":[],"335":[],"336":[],"337":[],"338":[],"341":[],"342":[],"344":[],"345":[],"346":[],"347":[],"348":[],"349":[],"350":[],"352":[],"353":[],"354":[],"355":[],"356":[],"357":[],"358":[],"360":[],"361":[],"362":[],"363":[],"364":[],"365":[],"366":[],"367":[],"368":[],"369":[],"370":[],"371":[],"372":[],"373":[],"374":[],"375":[],"376":[],"377":[],"378":[],"379":[],"380":[],"381":[],"382":[],"383":[],"384":[],"385":[],"386":[],"387":[],"389":[],"390":[],"391":[],"393":[],"394":[],"395":[],"396":[],"397":[],"398":[],"399":[],"401":[],"402":[],"403":[],"404":[],"405":[],"406":[],"407":[],"408":[],"409":[],"410":[],"411":[],"412":[],"413":[],"414":[],"415":[],"416":[],"417":[],"418":[],"419":[],"420":[],"421":[],"422":[],"423":[],"424":[],"425":[],"427":[],"428":[],"429":[],"430":[],"431":[],"432":[],"433":[],"434":[],"435":[],"436":[],"437":[],"438":[],"439":[],"440":[],"441":[],"443":[],"444":[],"445":[],"446":[],"447":[],"448":[],"449":[],"450":[],"451":[],"452":[],"453":[],"454":[],"455":[],"456":[],"457":[],"458":[],"459":[],"460":[],"461":[],"462":[],"463":[],"464":[],"465":[],"466":[],"467":[],"468":[],"469":[],"470":[],"471":[],"472":[],"473":[],"474":[],"475":[],"476":[],"477":[],"478":[],"479":[],"480":[],"481":[],"482":[],"483":[],"484":[],"485":[],"487":[],"488":[],"489":[],"490":[],"491":[],"492":[],"493":[],"494":[],"495":[],"496":[],"497":[],"498":[],"499":[],"500":[],"501":[],"502":[],"503":[],"504":[],"505":[],"506":[],"507":[],"508":[],"509":[],"510":[],"511":[],"512":[],"513":[],"514":[],"515":[],"517":[],"518":[],"519":[],"520":[],"521":[],"522":[],"523":[],"524":[],"525":[],"526":[],"527":[],"528":[],"530":[],"531":[],"532":[],"533":[],"534":[],"535":[],"536":[],"538":[],"539":[],"540":[],"541":[],"542":[],"543":[],"545":[],"546":[],"547":[],"548":[],"549":[],"550":[],"551":[],"554":[],"555":[],"556":[],"557":[],"558":[],"559":[],"560":[]},"count":"8986","facets":{"country":[{"count":"3491","filter":"DE","formatted":"DE"},{"count":"1189","filter":"NL","formatted":"NL"},{"count":"1118","filter":"FR","formatted":"FR"},{"count":"429","filter":"CZ","formatted":"CZ"},{"count":"416","filter":"CH","formatted":"CH"},{"count":"395","filter":"GB","formatted":"GB"},{"count":"273","filter":"IT","formatted":"IT"},{"count":"236","filter":"BE","formatted":"BE"},{"count":"204","filter":"ES","formatted":"ES"},{"count":"203","filter":"XC","formatted":"XC"},{"count":"168","filter":"PL","formatted":"PL"},{"count":"105","filter":"XE","formatted":"XE"},{"count":"91","filter":"GR","formatted":"GR"},{"count":"83","filter":"US","formatted":"US"},{"count":"60","filter":"AT","formatted":"AT"},{"count":"47","filter":"SE","formatted":"SE"},{"count":"45","filter":"BR","formatted":"BR"},{"count":"37","filter":"CL","formatted":"CL"},{"count":"34","filter":"SK","formatted":"SK"},{"count":"31","filter":"AU","formatted":"AU"},{"count":"30","filter":"XI","formatted":"XI"},{"count":"28","filter":"FI","formatted":"FI"},{"count":"27","filter":"PT","formatted":"PT"},{"count":"24","filter":"CA","formatted":"CA"},{"count":"19","filter":"MX","formatted":"MX"},{"count":"17","filter":"SI","formatted":"SI"},{"count":"17","filter":"HU","formatted":"HU"},{"count":"16","filter":"TR","formatted":"TR"},{"count":"16","filter":"HR","formatted":"HR"},{"count":"15","filter":"IE","formatted":"IE"},{"count":"14","filter":"AR","formatted":"AR"},{"count":"13","filter":"RS","formatted":"RS"},{"count":"10","filter":"CO","formatted":"CO"},{"count":"9","filter":"UY","formatted":"UY"},{"count":"7","filter":"DK","formatted":"DK"},{"count":"7","filter":"MK","formatted":"MK"},{"count":"6","filter":"NO","formatted":"NO"},{"count":"5","filter":"RO","formatted":"RO"},{"count":"5","filter":"RU","formatted":"RU"},{"count":"5","filter":"PE","formatted":"PE"},{"count":"4","filter":"LT","formatted":"LT"},{"count":"4","filter":"EE","formatted":"EE"},{"count":"4","filter":"BG","formatted":"BG"},{"count":"3","filter":"LV","formatted":"LV"},{"count":"3","filter":"MA","formatted":"MA"},{"count":"3","filter":"XK","formatted":"XK"},{"count":"2","filter":"CN","formatted":"CN"},{"count":"2","filter":"UA","formatted":"UA"},{"count":"2","filter":"BA","formatted":"BA"},{"count":"2","filter":"BO","formatted":"BO"}],"administrative_area":[{"count":"861","filter":"","formatted":""},{"count":"20","filter":"RS","formatted":"RS"},{"count":"19","filter":"NY","formatted":"NY"},{"count":"15","filter":"CA","formatted":"CA"},{"count":"12","filter":"NSW","formatted":"NSW"},{"count":"10","filter":"QC","formatted":"QC"},{"count":"9","filter":"VIC","formatted":"VIC"},{"count":"9","filter":"WA","formatted":"WA"},{"count":"8","filter":"TX","formatted":"TX"},{"count":"7","filter":"SP","formatted":"SP"},{"count":"7","filter":"London","formatted":"London"},{"count":"7","filter":"OR","formatted":"OR"},{"count":"6","filter":"Provincia de Madrid","formatted":"Provincia de Madrid"},{"count":"6","filter":"NC","formatted":"NC"},{"count":"5","filter":"RJ","formatted":"RJ"},{"count":"4","filter":"MG","formatted":"MG"},{"count":"4","filter":"Select","formatted":"Select"},{"count":"4","filter":"Cleveland","formatted":"Cleveland"},{"count":"4","filter":"UK","formatted":"UK"},{"count":"4","filter":"MA","formatted":"MA"},{"count":"3","filter":"PA","formatted":"PA"},{"count":"3","filter":"QLD","formatted":"QLD"},{"count":"3","filter":"D%2EF%2E","formatted":"D.F."},{"count":"3","filter":"RM","formatted":"RM"},{"count":"3","filter":"Santa Fe","formatted":"Santa Fe"},{"count":"3","filter":"Buenos Aires","formatted":"Buenos Aires"},{"count":"2","filter":"MO","formatted":"MO"},{"count":"2","filter":"Shanghai","formatted":"Shanghai"},{"count":"2","filter":"PG","formatted":"PG"},{"count":"2","filter":"Greater London","formatted":"Greater London"},{"count":"2","filter":"MT","formatted":"MT"},{"count":"2","filter":"PI","formatted":"PI"},{"count":"2","filter":"-","formatted":"-"},{"count":"2","filter":"BC","formatted":"BC"},{"count":"2","filter":"Illes Balears","formatted":"Illes Balears"},{"count":"2","filter":"NS","formatted":"NS"},{"count":"2","filter":"RI","formatted":"RI"},{"count":"2","filter":"BO","formatted":"BO"},{"count":"2","filter":"Jalisco","formatted":"Jalisco"},{"count":"2","filter":"Kent","formatted":"Kent"},{"count":"2","filter":"United Kingdom","formatted":"United Kingdom"},{"count":"2","filter":"LA","formatted":"LA"},{"count":"2","filter":"Dorset","formatted":"Dorset"},{"count":"2","filter":"Northern Ireland","formatted":"Northern Ireland"},{"count":"2","filter":"Durham","formatted":"Durham"},{"count":"2","filter":"ON","formatted":"ON"},{"count":"1","filter":"Wales","formatted":"Wales"},{"count":"1","filter":"Espa\u00f1a","formatted":"Espa\u00f1a"},{"count":"1","filter":"guadalajara","formatted":"guadalajara"},{"count":"1","filter":"CS","formatted":"CS"}],"locality":[{"count":"2076","filter":"Berlin","formatted":"Berlin"},{"count":"766","filter":"Amsterdam","formatted":"Amsterdam"},{"count":"625","filter":"K\u00f6ln","formatted":"K\u00f6ln"},{"count":"619","filter":"","formatted":""},{"count":"279","filter":"Paris","formatted":"Paris"},{"count":"202","filter":"Prague","formatted":"Prague"},{"count":"202","filter":"London","formatted":"London"},{"count":"140","filter":"Bruxelles","formatted":"Bruxelles"},{"count":"133","filter":"Barcelona","formatted":"Barcelona"},{"count":"124","filter":"Toulouse","formatted":"Toulouse"},{"count":"123","filter":"Marseille","formatted":"Marseille"},{"count":"108","filter":"Lyon","formatted":"Lyon"},{"count":"88","filter":"Karlsruhe","formatted":"Karlsruhe"},{"count":"81","filter":"Z\u00fcrich","formatted":"Z\u00fcrich"},{"count":"71","filter":"Luzern","formatted":"Luzern"},{"count":"69","filter":"Caen","formatted":"Caen"},{"count":"60","filter":"Madrid","formatted":"Madrid"},{"count":"52","filter":"Utrecht","formatted":"Utrecht"},{"count":"48","filter":"Montpellier","formatted":"Montpellier"},{"count":"46","filter":"Warszawa","formatted":"Warszawa"},{"count":"44","filter":"Athens","formatted":"Athens"},{"count":"43","filter":"Bern","formatted":"Bern"},{"count":"41","filter":"Rotterdam","formatted":"Rotterdam"},{"count":"41","filter":"Regensburg","formatted":"Regensburg"},{"count":"39","filter":"Roma","formatted":"Roma"},{"count":"39","filter":"Groningen","formatted":"Groningen"},{"count":"39","filter":"Den Haag","formatted":"Den Haag"},{"count":"38","filter":"Praha","formatted":"Praha"},{"count":"38","filter":"Wroc\u0142aw","formatted":"Wroc\u0142aw"},{"count":"35","filter":"Dijon","formatted":"Dijon"},{"count":"35","filter":"Bordeaux","formatted":"Bordeaux"},{"count":"35","filter":"Gent","formatted":"Gent"},{"count":"34","filter":"Brno","formatted":"Brno"},{"count":"33","filter":"Basel","formatted":"Basel"},{"count":"30","filter":"Bremen","formatted":"Bremen"},{"count":"29","filter":"Grenoble","formatted":"Grenoble"},{"count":"27","filter":"Nantes","formatted":"Nantes"},{"count":"26","filter":"Santiago","formatted":"Santiago"},{"count":"26","filter":"Torino","formatted":"Torino"},{"count":"25","filter":"Stockholm","formatted":"Stockholm"},{"count":"24","filter":"Milano","formatted":"Milano"},{"count":"24","filter":"Potsdam","formatted":"Potsdam"},{"count":"23","filter":"Ostrava","formatted":"Ostrava"},{"count":"23","filter":"Graz","formatted":"Graz"},{"count":"23","filter":"Bilbo","formatted":"Bilbo"},{"count":"22","filter":"Winterthur","formatted":"Winterthur"},{"count":"21","filter":"Rostock","formatted":"Rostock"},{"count":"20","filter":"Gen\u00e8ve","formatted":"Gen\u00e8ve"},{"count":"19","filter":"Sevilla","formatted":"Sevilla"},{"count":"19","filter":"Porto Alegre","formatted":"Porto Alegre"}],"dependent_locality":[{"count":"27","filter":"","formatted":""},{"count":"2","filter":"Vila Isabel","formatted":"Vila Isabel"},{"count":"2","filter":"Cidade Baixa","formatted":"Cidade Baixa"},{"count":"1","filter":"S\u00e3o Lucas","formatted":"S\u00e3o Lucas"},{"count":"1","filter":"Vila Buarque","formatted":"Vila Buarque"},{"count":"1","filter":"Bairro Azenha","formatted":"Bairro Azenha"},{"count":"1","filter":"Bairro Ferry Boat, Vila Santa Rosa","formatted":"Bairro Ferry Boat, Vila Santa Rosa"},{"count":"1","filter":"Butant\u00e3","formatted":"Butant\u00e3"},{"count":"1","filter":"Centro Hist\u00f3rico","formatted":"Centro Hist\u00f3rico"},{"count":"1","filter":"Cristo Rei","formatted":"Cristo Rei"},{"count":"1","filter":"Humait\u00e1","formatted":"Humait\u00e1"},{"count":"1","filter":"Lami","formatted":"Lami"},{"count":"1","filter":"Lapa","formatted":"Lapa"},{"count":"1","filter":"Maracan\u00e3","formatted":"Maracan\u00e3"},{"count":"1","filter":"Menino Deus","formatted":"Menino Deus"},{"count":"1","filter":"Parque Ge\u00f3rgia","formatted":"Parque Ge\u00f3rgia"},{"count":"1","filter":"Ponte Preta","formatted":"Ponte Preta"}]}}